{
  "kind": "collectionType",
  "collectionName": "flip_cards",
  "info": {
    "singularName": "flip-card",
    "pluralName": "flip-cards",
    "displayName": "Flip_card",
    "description": ""
  },
  "options": {
    "draftAndPublish": true
  },
  "pluginOptions": {},
  "attributes": {
    "img": {
      "type": "media",
      "multiple": false,
      "required": true,
      "allowedTypes": [
        "images",
        "files",
        "videos",
        "audios"
      ]
    },
    "title": {
      "type": "string",
      "required": true
    },
    "description_text": {
      "type": "text",
      "required": true
    },
    "cups": {
      "type": "component",
      "repeatable": true,
      "component": "cards.sup"
    },
    "description_rich_text": {
      "type": "richtext"
    },
    "description": {
      "type": "component",
      "repeatable": false,
      "component": "single.description"
    }
  }
}
